<?xml version="1.0"?>
<prayertimes>
	<country name="Palau">
		<city name="70 Islands">
			<state></state>
			<latitude>71805</latitude>
			<longitude>1342722</longitude>
			<timezone>900</timezone>
			<daylight>0</daylight>
		</city>
		<city name="Calamadei">
			<state></state>
			<latitude>76371</latitude>
			<longitude>1346535</longitude>
			<timezone>900</timezone>
			<daylight>0</daylight>
		</city>
		<city name="Cape Aitaburai">
			<state></state>
			<latitude>71449</latitude>
			<longitude>1343907</longitude>
			<timezone>900</timezone>
			<daylight>0</daylight>
		</city>
		<city name="Cape Babelthuap">
			<state></state>
			<latitude>77349</latitude>
			<longitude>1346271</longitude>
			<timezone>900</timezone>
			<daylight>0</daylight>
		</city>
		<city name="Cape Bokurgel">
			<state></state>
			<latitude>74549</latitude>
			<longitude>1344710</longitude>
			<timezone>900</timezone>
			<daylight>0</daylight>
		</city>
		<city name="Cape Gabadaguru">
			<state></state>
			<latitude>72852</latitude>
			<longitude>1343388</longitude>
			<timezone>900</timezone>
			<daylight>0</daylight>
		</city>
		<city name="Cape Medorom">
			<state></state>
			<latitude>68977</latitude>
			<longitude>1341293</longitude>
			<timezone>900</timezone>
			<daylight>0</daylight>
		</city>
		<city name="Cape Ngara">
			<state></state>
			<latitude>69074</latitude>
			<longitude>1341341</longitude>
			<timezone>900</timezone>
			<daylight>0</daylight>
		</city>
		<city name="Cape Ngatpokul">
			<state></state>
			<latitude>69221</latitude>
			<longitude>1341593</longitude>
			<timezone>900</timezone>
			<daylight>0</daylight>
		</city>
		<city name="Cape Pkula-Beap">
			<state></state>
			<latitude>73071</latitude>
			<longitude>1345016</longitude>
			<timezone>900</timezone>
			<daylight>0</daylight>
		</city>
		<city name="Cape Pkulangelul">
			<state></state>
			<latitude>69293</latitude>
			<longitude>1341324</longitude>
			<timezone>900</timezone>
			<daylight>0</daylight>
		</city>
		<city name="Cape Pkulatap-Rival">
			<state></state>
			<latitude>75580</latitude>
			<longitude>1346449</longitude>
			<timezone>900</timezone>
			<daylight>0</daylight>
		</city>
		<city name="Carapellas">
			<state></state>
			<latitude>80513</latitude>
			<longitude>1347082</longitude>
			<timezone>900</timezone>
			<daylight>0</daylight>
		</city>
		<city name="Carp Island">
			<state></state>
			<latitude>70988</latitude>
			<longitude>1342821</longitude>
			<timezone>900</timezone>
			<daylight>0</daylight>
		</city>
		<city name="Carteret">
			<state></state>
			<latitude>29082</latitude>
			<longitude>1318266</longitude>
			<timezone>900</timezone>
			<daylight>0</daylight>
		</city>
		<city name="Chechol">
			<state></state>
			<latitude>73585</latitude>
			<longitude>1344516</longitude>
			<timezone>900</timezone>
			<daylight>0</daylight>
		</city>
		<city name="Chelbacheb">
			<state></state>
			<latitude>72432</latitude>
			<longitude>1343099</longitude>
			<timezone>900</timezone>
			<daylight>0</daylight>
		</city>
		<city name="Chelechui">
			<state></state>
			<latitude>74285</latitude>
			<longitude>1345032</longitude>
			<timezone>900</timezone>
			<daylight>0</daylight>
		</city>
		<city name="Cheleos">
			<state></state>
			<latitude>77318</latitude>
			<longitude>1346268</longitude>
			<timezone>900</timezone>
			<daylight>0</daylight>
		</city>
		<city name="Cheleu">
			<state></state>
			<latitude>71174</latitude>
			<longitude>1342510</longitude>
			<timezone>900</timezone>
			<daylight>0</daylight>
		</city>
		<city name="Chemoi">
			<state></state>
			<latitude>71980</latitude>
			<longitude>1343932</longitude>
			<timezone>900</timezone>
			<daylight>0</daylight>
		</city>
		<city name="Chesau">
			<state></state>
			<latitude>72093</latitude>
			<longitude>1344485</longitude>
			<timezone>900</timezone>
			<daylight>0</daylight>
		</city>
		<city name="Chiangel">
			<state></state>
			<latitude>80905</latitude>
			<longitude>1347263</longitude>
			<timezone>900</timezone>
			<daylight>0</daylight>
		</city>
		<city name="Chiyou">
			<state></state>
			<latitude>76980</latitude>
			<longitude>1346430</longitude>
			<timezone>900</timezone>
			<daylight>0</daylight>
		</city>
		<city name="Chochimer">
			<state></state>
			<latitude>77946</latitude>
			<longitude>1345802</longitude>
			<timezone>900</timezone>
			<daylight>0</daylight>
		</city>
		<city name="Chol">
			<state></state>
			<latitude>76782</latitude>
			<longitude>1346427</longitude>
			<timezone>900</timezone>
			<daylight>0</daylight>
		</city>
		<city name="Chol Elementary School">
			<state></state>
			<latitude>76827</latitude>
			<longitude>1346474</longitude>
			<timezone>900</timezone>
			<daylight>0</daylight>
		</city>
		<city name="Cholkong">
			<state></state>
			<latitude>76682</latitude>
			<longitude>1346016</longitude>
			<timezone>900</timezone>
			<daylight>0</daylight>
		</city>
		<city name="Chomedokl">
			<state></state>
			<latitude>72368</latitude>
			<longitude>1344068</longitude>
			<timezone>900</timezone>
			<daylight>0</daylight>
		</city>
		<city name="Chomet Ubet">
			<state></state>
			<latitude>75266</latitude>
			<longitude>1345099</longitude>
			<timezone>900</timezone>
			<daylight>0</daylight>
		</city>
		<city name="Chongelungel">
			<state></state>
			<latitude>73538</latitude>
			<longitude>1345404</longitude>
			<timezone>900</timezone>
			<daylight>0</daylight>
		</city>
		<city name="Chowid">
			<state></state>
			<latitude>71977</latitude>
			<longitude>1343882</longitude>
			<timezone>900</timezone>
			<daylight>0</daylight>
		</city>
		<city name="Chudel">
			<state></state>
			<latitude>71391</latitude>
			<longitude>1344016</longitude>
			<timezone>900</timezone>
			<daylight>0</daylight>
		</city>
		<city name="Coaengal">
			<state></state>
			<latitude>75032</latitude>
			<longitude>1346441</longitude>
			<timezone>900</timezone>
			<daylight>0</daylight>
		</city>
		<city name="Cormoran Reef">
			<state></state>
			<latitude>78527</latitude>
			<longitude>1345291</longitude>
			<timezone>900</timezone>
			<daylight>0</daylight>
		</city>
		<city name="Dabadora">
			<state></state>
			<latitude>74083</latitude>
			<longitude>1345411</longitude>
			<timezone>900</timezone>
			<daylight>0</daylight>
		</city>
		<city name="Dabadoru">
			<state></state>
			<latitude>74100</latitude>
			<longitude>1345267</longitude>
			<timezone>900</timezone>
			<daylight>0</daylight>
		</city>
		<city name="Daerur">
			<state></state>
			<latitude>73708</latitude>
			<longitude>1344408</longitude>
			<timezone>900</timezone>
			<daylight>0</daylight>
		</city>
		<city name="Daimechesengel">
			<state></state>
			<latitude>76531</latitude>
			<longitude>1345917</longitude>
			<timezone>900</timezone>
			<daylight>0</daylight>
		</city>
		<city name="Dechor">
			<state></state>
			<latitude>76344</latitude>
			<longitude>1345933</longitude>
			<timezone>900</timezone>
			<daylight>0</daylight>
		</city>
		<city name="Delebog">
			<state></state>
			<latitude>77103</latitude>
			<longitude>1346486</longitude>
			<timezone>900</timezone>
			<daylight>0</daylight>
		</city>
		<city name="Delutaog">
			<state></state>
			<latitude>69125</latitude>
			<longitude>1341361</longitude>
			<timezone>900</timezone>
			<daylight>0</daylight>
		</city>
		<city name="Demul Iou">
			<state></state>
			<latitude>71783</latitude>
			<longitude>1344033</longitude>
			<timezone>900</timezone>
			<daylight>0</daylight>
		</city>
		<city name="Denges Passage">
			<state></state>
			<latitude>71311</latitude>
			<longitude>1343739</longitude>
			<timezone>900</timezone>
			<daylight>0</daylight>
		</city>
		<city name="Derromel">
			<state></state>
			<latitude>73636</latitude>
			<longitude>1344733</longitude>
			<timezone>900</timezone>
			<daylight>0</daylight>
		</city>
		<city name="Desomel">
			<state></state>
			<latitude>73700</latitude>
			<longitude>1344458</longitude>
			<timezone>900</timezone>
			<daylight>0</daylight>
		</city>
		<city name="Dibard">
			<state></state>
			<latitude>74200</latitude>
			<longitude>1346350</longitude>
			<timezone>900</timezone>
			<daylight>0</daylight>
		</city>
		<city name="Diluches Meded">
			<state></state>
			<latitude>81031</latitude>
			<longitude>1347072</longitude>
			<timezone>900</timezone>
			<daylight>0</daylight>
		</city>
		<city name="Dimes">
			<state></state>
			<latitude>80853</latitude>
			<longitude>1347256</longitude>
			<timezone>900</timezone>
			<daylight>0</daylight>
		</city>
		<city name="Dlebebai">
			<state></state>
			<latitude>73492</latitude>
			<longitude>1345606</longitude>
			<timezone>900</timezone>
			<daylight>0</daylight>
		</city>
		<city name="Dmasech">
			<state></state>
			<latitude>71389</latitude>
			<longitude>1342400</longitude>
			<timezone>900</timezone>
			<daylight>0</daylight>
		</city>
		<city name="Dngebard">
			<state></state>
			<latitude>73664</latitude>
			<longitude>1345875</longitude>
			<timezone>900</timezone>
			<daylight>0</daylight>
		</city>
		<city name="Dobesang Island">
			<state></state>
			<latitude>73594</latitude>
			<longitude>1344489</longitude>
			<timezone>900</timezone>
			<daylight>0</daylight>
		</city>
		<city name="Dormechol">
			<state></state>
			<latitude>75189</latitude>
			<longitude>1346317</longitude>
			<timezone>900</timezone>
			<daylight>0</daylight>
		</city>
		<city name="Doro Island">
			<state></state>
			<latitude>73569</latitude>
			<longitude>1344936</longitude>
			<timezone>900</timezone>
			<daylight>0</daylight>
		</city>
		<city name="Doro-To">
			<state></state>
			<latitude>73467</latitude>
			<longitude>1344922</longitude>
			<timezone>900</timezone>
			<daylight>0</daylight>
		</city>
		<city name="Duruokowaru Island">
			<state></state>
			<latitude>71264</latitude>
			<longitude>1343864</longitude>
			<timezone>900</timezone>
			<daylight>0</daylight>
		</city>
		<city name="Ebaduls Pier">
			<state></state>
			<latitude>73584</latitude>
			<longitude>1344868</longitude>
			<timezone>900</timezone>
			<daylight>0</daylight>
		</city>
		<city name="Echang">
			<state></state>
			<latitude>73537</latitude>
			<longitude>1344590</longitude>
			<timezone>900</timezone>
			<daylight>0</daylight>
		</city>
		<city name="Edchib">
			<state></state>
			<latitude>72309</latitude>
			<longitude>1342437</longitude>
			<timezone>900</timezone>
			<daylight>0</daylight>
		</city>
		<city name="Edeng">
			<state></state>
			<latitude>73934</latitude>
			<longitude>1345601</longitude>
			<timezone>900</timezone>
			<daylight>0</daylight>
		</city>
		<city name="Eil Malik">
			<state></state>
			<latitude>71626</latitude>
			<longitude>1343670</longitude>
			<timezone>900</timezone>
			<daylight>0</daylight>
		</city>
		<city name="Eil Malk">
			<state></state>
			<latitude>71476</latitude>
			<longitude>1343909</longitude>
			<timezone>900</timezone>
			<daylight>0</daylight>
		</city>
		<city name="Eimelik">
			<state></state>
			<latitude>74101</latitude>
			<longitude>1345101</longitude>
			<timezone>900</timezone>
			<daylight>0</daylight>
		</city>
		<city name="Eitelblong">
			<state></state>
			<latitude>73398</latitude>
			<longitude>1345229</longitude>
			<timezone>900</timezone>
			<daylight>0</daylight>
		</city>
		<city name="Ejinkoto Shoal">
			<state></state>
			<latitude>78979</latitude>
			<longitude>1345970</longitude>
			<timezone>900</timezone>
			<daylight>0</daylight>
		</city>
		<city name="Elecbue">
			<state></state>
			<latitude>74398</latitude>
			<longitude>1344873</longitude>
			<timezone>900</timezone>
			<daylight>0</daylight>
		</city>
		<city name="Elechol ra Bkulabeluu">
			<state></state>
			<latitude>70012</latitude>
			<longitude>1342301</longitude>
			<timezone>900</timezone>
			<daylight>0</daylight>
		</city>
		<city name="Elechol ra Debed">
			<state></state>
			<latitude>70207</latitude>
			<longitude>1342307</longitude>
			<timezone>900</timezone>
			<daylight>0</daylight>
		</city>
		<city name="Elechol ra Imelechol">
			<state></state>
			<latitude>70512</latitude>
			<longitude>1342734</longitude>
			<timezone>900</timezone>
			<daylight>0</daylight>
		</city>
		<city name="Elechol ra Ngeriois">
			<state></state>
			<latitude>69126</latitude>
			<longitude>1341568</longitude>
			<timezone>900</timezone>
			<daylight>0</daylight>
		</city>
		<city name="Elechol ra Ngetechirur">
			<state></state>
			<latitude>70537</latitude>
			<longitude>1342657</longitude>
			<timezone>900</timezone>
			<daylight>0</daylight>
		</city>
		<city name="Elechol ra Nguruhei">
			<state></state>
			<latitude>69232</latitude>
			<longitude>1341346</longitude>
			<timezone>900</timezone>
			<daylight>0</daylight>
		</city>
		<city name="Elibel">
			<state></state>
			<latitude>80487</latitude>
			<longitude>1347065</longitude>
			<timezone>900</timezone>
			<daylight>0</daylight>
		</city>
		<city name="Elodesachel">
			<state></state>
			<latitude>73562</latitude>
			<longitude>1345090</longitude>
			<timezone>900</timezone>
			<daylight>0</daylight>
		</city>
		<city name="Emeleol">
			<state></state>
			<latitude>70473</latitude>
			<longitude>1342715</longitude>
			<timezone>900</timezone>
			<daylight>0</daylight>
		</city>
		<city name="Emesiochel">
			<state></state>
			<latitude>72645</latitude>
			<longitude>1343476</longitude>
			<timezone>900</timezone>
			<daylight>0</daylight>
		</city>
		<city name="Emieangl">
			<state></state>
			<latitude>74540</latitude>
			<longitude>1344834</longitude>
			<timezone>900</timezone>
			<daylight>0</daylight>
		</city>
		<city name="Emis">
			<state></state>
			<latitude>74768</latitude>
			<longitude>1345434</longitude>
			<timezone>900</timezone>
			<daylight>0</daylight>
		</city>
		<city name="Engas">
			<state></state>
			<latitude>74848</latitude>
			<longitude>1344973</longitude>
			<timezone>900</timezone>
			<daylight>0</daylight>
		</city>
		<city name="Engkasar">
			<state></state>
			<latitude>74776</latitude>
			<longitude>1346173</longitude>
			<timezone>900</timezone>
			<daylight>0</daylight>
		</city>
		<city name="Eomogan">
			<state></state>
			<latitude>71440</latitude>
			<longitude>1343145</longitude>
			<timezone>900</timezone>
			<daylight>0</daylight>
		</city>
		<city name="Erakkueeru Island">
			<state></state>
			<latitude>75126</latitude>
			<longitude>1345048</longitude>
			<timezone>900</timezone>
			<daylight>0</daylight>
		</city>
		<city name="Erengoll">
			<state></state>
			<latitude>77726</latitude>
			<longitude>1345809</longitude>
			<timezone>900</timezone>
			<daylight>0</daylight>
		</city>
		<city name="Ertong">
			<state></state>
			<latitude>75159</latitude>
			<longitude>1346240</longitude>
			<timezone>900</timezone>
			<daylight>0</daylight>
		</city>
		<city name="Erusumu Mountain">
			<state></state>
			<latitude>75662</latitude>
			<longitude>1346046</longitude>
			<timezone>900</timezone>
			<daylight>0</daylight>
		</city>
		<city name="Etichiech">
			<state></state>
			<latitude>74440</latitude>
			<longitude>1345232</longitude>
			<timezone>900</timezone>
			<daylight>0</daylight>
		</city>
		<city name="Etiruir">
			<state></state>
			<latitude>75287</latitude>
			<longitude>1345376</longitude>
			<timezone>900</timezone>
			<daylight>0</daylight>
		</city>
		<city name="Euakor">
			<state></state>
			<latitude>73590</latitude>
			<longitude>1344540</longitude>
			<timezone>900</timezone>
			<daylight>0</daylight>
		</city>
		<city name="Euchelel Ngeruangl">
			<state></state>
			<latitude>81268</latitude>
			<longitude>1346851</longitude>
			<timezone>900</timezone>
			<daylight>0</daylight>
		</city>
		<city name="Fanah">
			<state></state>
			<latitude>53627</latitude>
			<longitude>1322358</longitude>
			<timezone>900</timezone>
			<daylight>0</daylight>
		</city>
		<city name="Fannog">
			<state></state>
			<latitude>75102</latitude>
			<longitude>1344602</longitude>
			<timezone>900</timezone>
			<daylight>0</daylight>
		</city>
		<city name="Halahol Point">
			<state></state>
			<latitude>70565</latitude>
			<longitude>1342757</longitude>
			<timezone>900</timezone>
			<daylight>0</daylight>
		</city>
		<city name="Hasekisu Reef">
			<state></state>
			<latitude>76437</latitude>
			<longitude>1345771</longitude>
			<timezone>900</timezone>
			<daylight>0</daylight>
		</city>
		<city name="Hatohobei">
			<state></state>
			<latitude>30104</latitude>
			<longitude>1311854</longitude>
			<timezone>900</timezone>
			<daylight>0</daylight>
		</city>
		<city name="Helen Channel">
			<state></state>
			<latitude>28937</latitude>
			<longitude>1317673</longitude>
			<timezone>900</timezone>
			<daylight>0</daylight>
		</city>
		<city name="Hells Pocket">
			<state></state>
			<latitude>70540</latitude>
			<longitude>1342698</longitude>
			<timezone>900</timezone>
			<daylight>0</daylight>
		</city>
		<city name="Heren To">
			<state></state>
			<latitude>29887</latitude>
			<longitude>1318240</longitude>
			<timezone>900</timezone>
			<daylight>0</daylight>
		</city>
		<city name="Higashi">
			<state></state>
			<latitude>78229</latitude>
			<longitude>1346118</longitude>
			<timezone>900</timezone>
			<daylight>0</daylight>
		</city>
		<city name="Higashi-Suido">
			<state></state>
			<latitude>78576</latitude>
			<longitude>1346646</longitude>
			<timezone>900</timezone>
			<daylight>0</daylight>
		</city>
		<city name="Hiruge">
			<state></state>
			<latitude>73390</latitude>
			<longitude>1344951</longitude>
			<timezone>900</timezone>
			<daylight>0</daylight>
		</city>
		<city name="Hoimadelehesuh">
			<state></state>
			<latitude>72826</latitude>
			<longitude>1344093</longitude>
			<timezone>900</timezone>
			<daylight>0</daylight>
		</city>
		<city name="Hokusei-sho">
			<state></state>
			<latitude>79948</latitude>
			<longitude>1345526</longitude>
			<timezone>900</timezone>
			<daylight>0</daylight>
		</city>
		<city name="Honeymoon Beach">
			<state></state>
			<latitude>70115</latitude>
			<longitude>1342662</longitude>
			<timezone>900</timezone>
			<daylight>0</daylight>
		</city>
		<city name="Iebukel">
			<state></state>
			<latitude>77088</latitude>
			<longitude>1346483</longitude>
			<timezone>900</timezone>
			<daylight>0</daylight>
		</city>
		<city name="Iengel">
			<state></state>
			<latitude>77397</latitude>
			<longitude>1345772</longitude>
			<timezone>900</timezone>
			<daylight>0</daylight>
		</city>
		<city name="Ika">
			<state></state>
			<latitude>73430</latitude>
			<longitude>1344916</longitude>
			<timezone>900</timezone>
			<daylight>0</daylight>
		</city>
		<city name="Ikelau">
			<state></state>
			<latitude>73502</latitude>
			<longitude>1344866</longitude>
			<timezone>900</timezone>
			<daylight>0</daylight>
		</city>
		<city name="Ikerdeu">
			<state></state>
			<latitude>74897</latitude>
			<longitude>1346411</longitude>
			<timezone>900</timezone>
			<daylight>0</daylight>
		</city>
		<city name="Ilagual Cove">
			<state></state>
			<latitude>69272</latitude>
			<longitude>1341647</longitude>
			<timezone>900</timezone>
			<daylight>0</daylight>
		</city>
		<city name="Ilebei">
			<state></state>
			<latitude>76727</latitude>
			<longitude>1346402</longitude>
			<timezone>900</timezone>
			<daylight>0</daylight>
		</city>
		<city name="Ilut Pebul">
			<state></state>
			<latitude>73377</latitude>
			<longitude>1345008</longitude>
			<timezone>900</timezone>
			<daylight>0</daylight>
		</city>
		<city name="Imetang">
			<state></state>
			<latitude>77202</latitude>
			<longitude>1346447</longitude>
			<timezone>900</timezone>
			<daylight>0</daylight>
		</city>
		<city name="Irikl">
			<state></state>
			<latitude>73599</latitude>
			<longitude>1344644</longitude>
			<timezone>900</timezone>
			<daylight>0</daylight>
		</city>
		<city name="Irrai">
			<state></state>
			<latitude>73680</latitude>
			<longitude>1345683</longitude>
			<timezone>900</timezone>
			<daylight>0</daylight>
		</city>
		<city name="Irur">
			<state></state>
			<latitude>75844</latitude>
			<longitude>1345669</longitude>
			<timezone>900</timezone>
			<daylight>0</daylight>
		</city>
		<city name="Itab">
			<state></state>
			<latitude>73541</latitude>
			<longitude>1344611</longitude>
			<timezone>900</timezone>
			<daylight>0</daylight>
		</city>
		<city name="Itabchemingl">
			<state></state>
			<latitude>73372</latitude>
			<longitude>1345052</longitude>
			<timezone>900</timezone>
			<daylight>0</daylight>
		</city>
		<city name="Itaoch">
			<state></state>
			<latitude>74899</latitude>
			<longitude>1344927</longitude>
			<timezone>900</timezone>
			<daylight>0</daylight>
		</city>
		<city name="Itungelii">
			<state></state>
			<latitude>74852</latitude>
			<longitude>1345124</longitude>
			<timezone>900</timezone>
			<daylight>0</daylight>
		</city>
		<city name="Iuengrull">
			<state></state>
			<latitude>76716</latitude>
			<longitude>1346177</longitude>
			<timezone>900</timezone>
			<daylight>0</daylight>
		</city>
		<city name="Iungel">
			<state></state>
			<latitude>77316</latitude>
			<longitude>1346202</longitude>
			<timezone>900</timezone>
			<daylight>0</daylight>
		</city>
		<city name="Ivaiu">
			<state></state>
			<latitude>69022</latitude>
			<longitude>1341577</longitude>
			<timezone>900</timezone>
			<daylight>0</daylight>
		</city>
		<city name="Jimusho">
			<state></state>
			<latitude>69120</latitude>
			<longitude>1341400</longitude>
			<timezone>900</timezone>
			<daylight>0</daylight>
		</city>
		<city name="Koror">
			<state></state>
			<latitude>73440</latitude>
			<longitude>1344940</longitude>
			<timezone>900</timezone>
			<daylight>0</daylight>
		</city>
		<city name="Koror Hafen">
			<state></state>
			<latitude>73713</latitude>
			<longitude>1344899</longitude>
			<timezone>900</timezone>
			<daylight>0</daylight>
		</city>
		<city name="Koror Road">
			<state></state>
			<latitude>72815</latitude>
			<longitude>1344829</longitude>
			<timezone>900</timezone>
			<daylight>0</daylight>
		</city>
		<city name="Koror State">
			<state></state>
			<latitude>73440</latitude>
			<longitude>1344857</longitude>
			<timezone>900</timezone>
			<daylight>0</daylight>
		</city>
		<city name="Kororu-to">
			<state></state>
			<latitude>73532</latitude>
			<longitude>1345051</longitude>
			<timezone>900</timezone>
			<daylight>0</daylight>
		</city>
		<city name="Lademisang">
			<state></state>
			<latitude>70189</latitude>
			<longitude>1342483</longitude>
			<timezone>900</timezone>
			<daylight>0</daylight>
		</city>
		<city name="Lild">
			<state></state>
			<latitude>75175</latitude>
			<longitude>1345050</longitude>
			<timezone>900</timezone>
			<daylight>0</daylight>
		</city>
		<city name="Limestone Ridge">
			<state></state>
			<latitude>70525</latitude>
			<longitude>1342697</longitude>
			<timezone>900</timezone>
			<daylight>0</daylight>
		</city>
		<city name="Lkes">
			<state></state>
			<latitude>69414</latitude>
			<longitude>1342108</longitude>
			<timezone>900</timezone>
			<daylight>0</daylight>
		</city>
		<city name="Llebuchel">
			<state></state>
			<latitude>73558</latitude>
			<longitude>1344525</longitude>
			<timezone>900</timezone>
			<daylight>0</daylight>
		</city>
		<city name="Lmetmellasch">
			<state></state>
			<latitude>76139</latitude>
			<longitude>1346441</longitude>
			<timezone>900</timezone>
			<daylight>0</daylight>
		</city>
		<city name="Queangal">
			<state></state>
			<latitude>80807</latitude>
			<longitude>1347238</longitude>
			<timezone>900</timezone>
			<daylight>0</daylight>
		</city>
		<city name="Rablissa">
			<state></state>
			<latitude>75242</latitude>
			<longitude>1346367</longitude>
			<timezone>900</timezone>
			<daylight>0</daylight>
		</city>
		<city name="Rael">
			<state></state>
			<latitude>73358</latitude>
			<longitude>1344931</longitude>
			<timezone>900</timezone>
			<daylight>0</daylight>
		</city>
		<city name="Rael Eding">
			<state></state>
			<latitude>74781</latitude>
			<longitude>1344656</longitude>
			<timezone>900</timezone>
			<daylight>0</daylight>
		</city>
		<city name="Rael Kedam">
			<state></state>
			<latitude>75281</latitude>
			<longitude>1345975</longitude>
			<timezone>900</timezone>
			<daylight>0</daylight>
		</city>
		<city name="Rael Orak">
			<state></state>
			<latitude>80500</latitude>
			<longitude>1347022</longitude>
			<timezone>900</timezone>
			<daylight>0</daylight>
		</city>
		<city name="Raelkelat">
			<state></state>
			<latitude>75078</latitude>
			<longitude>1344969</longitude>
			<timezone>900</timezone>
			<daylight>0</daylight>
		</city>
		<city name="Ratmau">
			<state></state>
			<latitude>76072</latitude>
			<longitude>1345697</longitude>
			<timezone>900</timezone>
			<daylight>0</daylight>
		</city>
		<city name="Rebaikesil">
			<state></state>
			<latitude>72253</latitude>
			<longitude>1343856</longitude>
			<timezone>900</timezone>
			<daylight>0</daylight>
		</city>
		<city name="Remoked">
			<state></state>
			<latitude>69870</latitude>
			<longitude>1342333</longitude>
			<timezone>900</timezone>
			<daylight>0</daylight>
		</city>
		<city name="Renrak">
			<state></state>
			<latitude>73722</latitude>
			<longitude>1345142</longitude>
			<timezone>900</timezone>
			<daylight>0</daylight>
		</city>
		<city name="Rikelau">
			<state></state>
			<latitude>71595</latitude>
			<longitude>1343275</longitude>
			<timezone>900</timezone>
			<daylight>0</daylight>
		</city>
		<city name="Rirs Bital">
			<state></state>
			<latitude>72245</latitude>
			<longitude>1343920</longitude>
			<timezone>900</timezone>
			<daylight>0</daylight>
		</city>
		<city name="Risong">
			<state></state>
			<latitude>73161</latitude>
			<longitude>1344858</longitude>
			<timezone>900</timezone>
			<daylight>0</daylight>
		</city>
		<city name="Rmegetbu">
			<state></state>
			<latitude>73706</latitude>
			<longitude>1344381</longitude>
			<timezone>900</timezone>
			<daylight>0</daylight>
		</city>
		<city name="Rois Buiel">
			<state></state>
			<latitude>75008</latitude>
			<longitude>1345083</longitude>
			<timezone>900</timezone>
			<daylight>0</daylight>
		</city>
		<city name="Rois Emiangel">
			<state></state>
			<latitude>74625</latitude>
			<longitude>1344964</longitude>
			<timezone>900</timezone>
			<daylight>0</daylight>
		</city>
		<city name="Rois Ketund">
			<state></state>
			<latitude>73622</latitude>
			<longitude>1344617</longitude>
			<timezone>900</timezone>
			<daylight>0</daylight>
		</city>
		<city name="Roiseaur">
			<state></state>
			<latitude>70428</latitude>
			<longitude>1342625</longitude>
			<timezone>900</timezone>
			<daylight>0</daylight>
		</city>
		<city name="Roisebong">
			<state></state>
			<latitude>74367</latitude>
			<longitude>1345039</longitude>
			<timezone>900</timezone>
			<daylight>0</daylight>
		</city>
		<city name="Roisersuul">
			<state></state>
			<latitude>74420</latitude>
			<longitude>1345897</longitude>
			<timezone>900</timezone>
			<daylight>0</daylight>
		</city>
		<city name="Roiskebesang">
			<state></state>
			<latitude>73581</latitude>
			<longitude>1344575</longitude>
			<timezone>900</timezone>
			<daylight>0</daylight>
		</city>
		<city name="Rrai">
			<state></state>
			<latitude>74436</latitude>
			<longitude>1346033</longitude>
			<timezone>900</timezone>
			<daylight>0</daylight>
		</city>
		<city name="Rurid Island">
			<state></state>
			<latitude>70414</latitude>
			<longitude>1342756</longitude>
			<timezone>900</timezone>
			<daylight>0</daylight>
		</city>
		<city name="Ryugu Island">
			<state></state>
			<latitude>73281</latitude>
			<longitude>1344947</longitude>
			<timezone>900</timezone>
			<daylight>0</daylight>
		</city>
		<city name="Saddle Mount">
			<state></state>
			<latitude>75012</latitude>
			<longitude>1344918</longitude>
			<timezone>900</timezone>
			<daylight>0</daylight>
		</city>
		<city name="Saipan Strait">
			<state></state>
			<latitude>69740</latitude>
			<longitude>1341990</longitude>
			<timezone>900</timezone>
			<daylight>0</daylight>
		</city>
		<city name="San Andres">
			<state></state>
			<latitude>53359</latitude>
			<longitude>1322326</longitude>
			<timezone>900</timezone>
			<daylight>0</daylight>
		</city>
		<city name="San Carlos">
			<state></state>
			<latitude>30207</latitude>
			<longitude>1311873</longitude>
			<timezone>900</timezone>
			<daylight>0</daylight>
		</city>
		<city name="Sanryo">
			<state></state>
			<latitude>73401</latitude>
			<longitude>1344990</longitude>
			<timezone>900</timezone>
			<daylight>0</daylight>
		</city>
		<city name="Schoman Harbor">
			<state></state>
			<latitude>71337</latitude>
			<longitude>1343407</longitude>
			<timezone>900</timezone>
			<daylight>0</daylight>
		</city>
		<city name="Sehesengel">
			<state></state>
			<latitude>72018</latitude>
			<longitude>1343737</longitude>
			<timezone>900</timezone>
			<daylight>0</daylight>
		</city>
		<city name="Sengall">
			<state></state>
			<latitude>73571</latitude>
			<longitude>1345098</longitude>
			<timezone>900</timezone>
			<daylight>0</daylight>
		</city>
		<city name="Simono Island">
			<state></state>
			<latitude>73387</latitude>
			<longitude>1345087</longitude>
			<timezone>900</timezone>
			<daylight>0</daylight>
		</city>
		<city name="Sngelokl Bay">
			<state></state>
			<latitude>71121</latitude>
			<longitude>1342690</longitude>
			<timezone>900</timezone>
			<daylight>0</daylight>
		</city>
		<city name="Sonsorol">
			<state></state>
			<latitude>53448</latitude>
			<longitude>1322282</longitude>
			<timezone>900</timezone>
			<daylight>0</daylight>
		</city>
		<city name="State of Airai">
			<state></state>
			<latitude>73782</latitude>
			<longitude>1345615</longitude>
			<timezone>900</timezone>
			<daylight>0</daylight>
		</city>
		<city name="State of Angaur">
			<state></state>
			<latitude>69115</latitude>
			<longitude>1341615</longitude>
			<timezone>900</timezone>
			<daylight>0</daylight>
		</city>
		<city name="State of Kayangel">
			<state></state>
			<latitude>80782</latitude>
			<longitude>1347198</longitude>
			<timezone>900</timezone>
			<daylight>0</daylight>
		</city>
		<city name="State of Melekeok">
			<state></state>
			<latitude>74948</latitude>
			<longitude>1346115</longitude>
			<timezone>900</timezone>
			<daylight>0</daylight>
		</city>
		<city name="State of Ngaraard">
			<state></state>
			<latitude>76282</latitude>
			<longitude>1346365</longitude>
			<timezone>900</timezone>
			<daylight>0</daylight>
		</city>
		<city name="State of Ngeremlengui">
			<state></state>
			<latitude>75532</latitude>
			<longitude>1345740</longitude>
			<timezone>900</timezone>
			<daylight>0</daylight>
		</city>
		<city name="State of Ngiwal">
			<state></state>
			<latitude>75615</latitude>
			<longitude>1346282</longitude>
			<timezone>900</timezone>
			<daylight>0</daylight>
		</city>
		<city name="Stations-Hafen">
			<state></state>
			<latitude>73448</latitude>
			<longitude>1344782</longitude>
			<timezone>900</timezone>
			<daylight>0</daylight>
		</city>
		<city name="Stephen Reef">
			<state></state>
			<latitude>72587</latitude>
			<longitude>1344868</longitude>
			<timezone>900</timezone>
			<daylight>0</daylight>
		</city>
		<city name="Uchelbeluu">
			<state></state>
			<latitude>72839</latitude>
			<longitude>1345603</longitude>
			<timezone>900</timezone>
			<daylight>0</daylight>
		</city>
		<city name="Ucheliungs">
			<state></state>
			<latitude>73195</latitude>
			<longitude>1345098</longitude>
			<timezone>900</timezone>
			<daylight>0</daylight>
		</city>
		<city name="Uchulalei">
			<state></state>
			<latitude>73611</latitude>
			<longitude>1344731</longitude>
			<timezone>900</timezone>
			<daylight>0</daylight>
		</city>
		<city name="Uchulameradel">
			<state></state>
			<latitude>75184</latitude>
			<longitude>1345020</longitude>
			<timezone>900</timezone>
			<daylight>0</daylight>
		</city>
		<city name="Uchulayas">
			<state></state>
			<latitude>73553</latitude>
			<longitude>1344748</longitude>
			<timezone>900</timezone>
			<daylight>0</daylight>
		</city>
		<city name="Ueno">
			<state></state>
			<latitude>73323</latitude>
			<longitude>1345081</longitude>
			<timezone>900</timezone>
			<daylight>0</daylight>
		</city>
		<city name="Ugula Kerregar">
			<state></state>
			<latitude>69292</latitude>
			<longitude>1341531</longitude>
			<timezone>900</timezone>
			<daylight>0</daylight>
		</city>
		<city name="Ugula Kerregar a Ilagiai">
			<state></state>
			<latitude>69334</latitude>
			<longitude>1341506</longitude>
			<timezone>900</timezone>
			<daylight>0</daylight>
		</city>
		<city name="Ukurakusetsu">
			<state></state>
			<latitude>75034</latitude>
			<longitude>1345159</longitude>
			<timezone>900</timezone>
			<daylight>0</daylight>
		</city>
		<city name="Ulach">
			<state></state>
			<latitude>80778</latitude>
			<longitude>1346964</longitude>
			<timezone>900</timezone>
			<daylight>0</daylight>
		</city>
		<city name="Ulapsagel">
			<state></state>
			<latitude>73200</latitude>
			<longitude>1344895</longitude>
			<timezone>900</timezone>
			<daylight>0</daylight>
		</city>
		<city name="Uler">
			<state></state>
			<latitude>70284</latitude>
			<longitude>1342617</longitude>
			<timezone>900</timezone>
			<daylight>0</daylight>
		</city>
		<city name="Ulimang">
			<state></state>
			<latitude>76334</latitude>
			<longitude>1346506</longitude>
			<timezone>900</timezone>
			<daylight>0</daylight>
		</city>
		<city name="Ulong">
			<state></state>
			<latitude>72870</latitude>
			<longitude>1343011</longitude>
			<timezone>900</timezone>
			<daylight>0</daylight>
		</city>
		<city name="Uluang">
			<state></state>
			<latitude>80767</latitude>
			<longitude>1347245</longitude>
			<timezone>900</timezone>
			<daylight>0</daylight>
		</city>
		<city name="Ulubosan">
			<state></state>
			<latitude>74998</latitude>
			<longitude>1344839</longitude>
			<timezone>900</timezone>
			<daylight>0</daylight>
		</city>
		<city name="Ulugol">
			<state></state>
			<latitude>76934</latitude>
			<longitude>1346500</longitude>
			<timezone>900</timezone>
			<daylight>0</daylight>
		</city>
		<city name="Uluong">
			<state></state>
			<latitude>76195</latitude>
			<longitude>1346295</longitude>
			<timezone>900</timezone>
			<daylight>0</daylight>
		</city>
		<city name="Ulutei">
			<state></state>
			<latitude>75284</latitude>
			<longitude>1345403</longitude>
			<timezone>900</timezone>
			<daylight>0</daylight>
		</city>
		<city name="Umurbrogol Mountain">
			<state></state>
			<latitude>70217</latitude>
			<longitude>1342464</longitude>
			<timezone>900</timezone>
			<daylight>0</daylight>
		</city>
		<city name="Unkaseri">
			<state></state>
			<latitude>72298</latitude>
			<longitude>1344048</longitude>
			<timezone>900</timezone>
			<daylight>0</daylight>
		</city>
		<city name="Urdmang">
			<state></state>
			<latitude>76228</latitude>
			<longitude>1345903</longitude>
			<timezone>900</timezone>
			<daylight>0</daylight>
		</city>
		<city name="Urecheruchel">
			<state></state>
			<latitude>71409</latitude>
			<longitude>1343784</longitude>
			<timezone>900</timezone>
			<daylight>0</daylight>
		</city>
		<city name="Urrakalong">
			<state></state>
			<latitude>77117</latitude>
			<longitude>1346367</longitude>
			<timezone>900</timezone>
			<daylight>0</daylight>
		</city>
		<city name="Urukdapel">
			<state></state>
			<latitude>73450</latitude>
			<longitude>1344617</longitude>
			<timezone>900</timezone>
			<daylight>0</daylight>
		</city>
		<city name="Uruktapi">
			<state></state>
			<latitude>72825</latitude>
			<longitude>1344367</longitude>
			<timezone>900</timezone>
			<daylight>0</daylight>
		</city>
		<city name="Urutoi-to">
			<state></state>
			<latitude>74873</latitude>
			<longitude>1346325</longitude>
			<timezone>900</timezone>
			<daylight>0</daylight>
		</city>
		<city name="Velasco Reef">
			<state></state>
			<latitude>83535</latitude>
			<longitude>1346243</longitude>
			<timezone>900</timezone>
			<daylight>0</daylight>
		</city>
		<city name="Warren Hastings Island">
			<state></state>
			<latitude>43361</latitude>
			<longitude>1323222</longitude>
			<timezone>900</timezone>
			<daylight>0</daylight>
		</city>
		<city name="West Entrance">
			<state></state>
			<latitude>79552</latitude>
			<longitude>1345075</longitude>
			<timezone>900</timezone>
			<daylight>0</daylight>
		</city>
		<city name="West Passage">
			<state></state>
			<latitude>75502</latitude>
			<longitude>1344808</longitude>
			<timezone>900</timezone>
			<daylight>0</daylight>
		</city>
		<city name="White Beach">
			<state></state>
			<latitude>70136</latitude>
			<longitude>1342294</longitude>
			<timezone>900</timezone>
			<daylight>0</daylight>
		</city>
		<city name="Wull">
			<state></state>
			<latitude>46713</latitude>
			<longitude>1319755</longitude>
			<timezone>900</timezone>
			<daylight>0</daylight>
		</city>
		<city name="Yalap">
			<state></state>
			<latitude>76454</latitude>
			<longitude>1346496</longitude>
			<timezone>900</timezone>
			<daylight>0</daylight>
		</city>
		<city name="Yar">
			<state></state>
			<latitude>72185</latitude>
			<longitude>1343824</longitude>
			<timezone>900</timezone>
			<daylight>0</daylight>
		</city>
		<city name="Yasi Island">
			<state></state>
			<latitude>73454</latitude>
			<longitude>1345121</longitude>
			<timezone>900</timezone>
			<daylight>0</daylight>
		</city>
		<city name="Yiilbelau">
			<state></state>
			<latitude>71282</latitude>
			<longitude>1342488</longitude>
			<timezone>900</timezone>
			<daylight>0</daylight>
		</city>
		<city name="Yo-suido">
			<state></state>
			<latitude>72132</latitude>
			<longitude>1343915</longitude>
			<timezone>900</timezone>
			<daylight>0</daylight>
		</city>
	</country>
</prayertimes>